deephaven/plugin/__init__.py
deephaven/plugin/js.py
deephaven/plugin/object_type.py
deephaven_plugin-0.6.0.dist-info/LICENSE
deephaven_plugin-0.6.0.dist-info/METADATA
deephaven_plugin-0.6.0.dist-info/WHEEL
deephaven_plugin-0.6.0.dist-info/entry_points.txt
deephaven_plugin-0.6.0.dist-info/top_level.txt
deephaven_plugin-0.6.0.dist-info/RECORD
