Metadata-Version: 2.1
Name: deephaven-plugin
Version: 0.6.0
Summary: Deephaven Plugin interface
Home-page: https://github.com/deephaven/deephaven-plugin
Author: Devin Smith
Author-email: devinsmith@deephaven.io
Project-URL: Source Code, https://github.com/deephaven/deephaven-plugin
Project-URL: Bug Tracker, https://github.com/deephaven/deephaven-plugin/issues
Keywords: deephaven,plugin
Platform: any
Classifier: Programming Language :: Python :: 3
Classifier: License :: OSI Approved :: Apache Software License
Classifier: Operating System :: OS Independent
Classifier: Environment :: Plugins
Classifier: Development Status :: 3 - Alpha
License-File: LICENSE
Requires-Dist: importlib-metadata >=3.6 ; python_version < "3.8"
